Workbook

Sheet Sheet1
B3: CLIENT
B4: PROJECT | D4: SRC / Western Camp
B5: SERVICE REQUISITION NO. | E5: COMMERCIAL EVALUATION TABLE - SUBCONTRACTING
B6: ITEM | D6: Training
E9: VENDOR | G9: KRTS LTD LLP | J9: RTG Tilmash LLP | M9: Apec Training Center LLP (offline) | P9: Intekko LLP | S9: "KazProf" Specialized Training Center LLP | V9: SafeLine LLP | Y9: Baitau LLP
E10: VENDOR
E11: OFFER REF. | G11: 1 | J11: 2 | M11: 3 | P11: 4 | S11: 5 | V11: 6 | Y11: 7
E12: CURRENCY / RATE
B13: S.NO | C13: ACTVITIY NO./ | D13: SERVICE DESCRIPTION | E13: TOTAL QTY | F13: Unit of measurement | G13: UNIT PRICE (KZT) | H13: TOTAL PRICE (KZT) | I13: REMARKS | J13: UNIT PRICE (KZT) | K13: TOTAL PRICE (KZT) | L13: REMARKS | M13: UNIT PRICE (KZT) | N13: TOTAL PRICE (KZT) | O13: REMARKS | P13: UNIT PRICE (KZT) | Q13: TOTAL PRICE (KZT) | R13: REMARKS | S13: UNIT PRICE (KZT) | T13: TOTAL PRICE (KZT) | U13: REMARKS | V13: UNIT PRICE (KZT) | W13: TOTAL PRICE (KZT) | X13: REMARKS | Y13: UNIT PRICE (KZT) | Z13: TOTAL PRICE (KZT) | AA13: REMARKS
B14: 1 | D14: Labour Code, Occupational Safety and Health Training | E14: 30 | F14: 7000 | H14: =G14*E14 | K14: =J14*E14 | N14: =M14*E14 | O14: Offline | Q14: =P14*E14 | T14: =S14*$E14 | U14: Online | W14: =V14*E14 | Z14: =Y14*E14
B15: 2 | D15: Training on the Law of the Republic of Kazakhstan "On Civil Protection" for Industrial Safety at Hazardous Production Facilities | E15: 30 | H15: =G15*E15 | K15: =J15*E15 | N15: =M15*E15 | O15: Offline | Q15: =P15*E15 | T15: =S15*$E15 | U15: Online | W15: =V15*E15 | Z15: =Y15*E15
B16: 3 | D16: Fire Safety Technical Minimum Training for Employees, Managers, and Persons Responsible for Fire Safety | E16: 30 | H16: =G16*E16 | K16: =J16*E16 | N16: =M16*E16 | O16: Offline | Q16: =P16*E16 | T16: =S16*$E16 | U16: Online | W16: =V16*E16 | Z16: =Y16*E16
B17: 4 | D17: Person Responsible for Safe Crane Operations | E17: 4 | H17: =G17*E17 | K17: =J17*E17 | N17: =M17*E17 | O17: Offline | Q17: =P17*E17 | T17: =S17*$E17 | U17: Online | W17: =V17*E17 | Z17: =Y17*E17
B18: 5 | D18: Person Responsible for the Technically Sound Condition of Lifting Cranes | E18: 4 | H18: =G18*E18 | K18: =J18*E18 | N18: =M18*E18 | O18: Offline | Q18: =P18*E18 | T18: =S18*$E18 | U18: Online | W18: =V18*E18 | Z18: =Y18*E18
B19: 6 | D19: Industrial Safety Rules for the Operation of Pressure Equipment | E19: 4 | H19: =G19*E19 | K19: =J19*E19 | N19: =M19*E19 | O19: Offline | Q19: =P19*E19 | T19: =S19*$E19 | U19: Online | W19: =V19*E19 | Z19: =Y19*E19
B20: 7 | D20: First Aid Training | E20: 3 | H20: =G20*E20 | K20: =J20*E20 | N20: =M20*E20 | Q20: =P20*E20 | R20: Offline only | T20: =S20*$E20 | U20: Online | W20: =V20*E20 | Z20: =Y20*E20
B21: 8 | D21: Electrical Safety: Technical Operation and Safety Rules (Groups IV and V) | E21: 5 | H21: =G21*E21 | K21: =J21*E21 | N21: =M21*E21 | O21: Offline | Q21: =P21*E21 | T21: =S21*$E21 | U21: Online | W21: =V21*E21 | Z21: =Y21*E21
B22: 9 | D22: Electrical Safety: Technical Operation and Safety Rules (Groups II and III) | E22: 10 | H22: =G22*E22 | K22: =J22*E22 | N22: =M22*E22 | O22: Offline | Q22: =P22*E22 | T22: =S22*$E22 | U22: Online | W22: =V22*E22 | Z22: =Y22*E22
B23: 10 | D23: Qualification Certificate | E23: 10 | H23: =G23*E23 | I23: The vendor calls the course "Knowledge Assessment and Professional Qualification Confirmation" | K23: =J23*E23 | N23: =M23*E23 | O23: Offline | Q23: =P23*E23 | T23: =S23*$E23 | U23: Online | W23: =V23*E23 | Z23: =Y23*E23
B24: TOTAL | H24: =SUM(H14:H23) | K24: =SUM(K14:K23) | N24: =SUM(N14:N23) | Q24: =SUM(Q14:Q23) | T24: =SUM(T14:T23) | W24: =SUM(W14:W23) | Z24: =SUM(Z14:Z23)
B25: DISCOUNT
B26: VAT | H26: 0.16 | K26: 0.16 | N26: 0.16 | Q26: 0.16 | Z26: 0.16
B27: GRAND TOTAL | G27: =H24*H26+H24 | J27: =K24*K26+K24 | M27: =N24*N26+N24 | P27: =Q24*Q26+Q24 | S27: =T24*T26+T24 | V27: =W24*W26+W24 | Y27: =Z24*Z26+Z24
B29: TERMS OF PAYMENT
B30: Mobilisation / Demobilisation Transport | G30: SUBCONTRACTOR | J30: SUBCONTRACTOR | M30: SUBCONTRACTOR | P30: SUBCONTRACTOR | S30: SUBCONTRACTOR | V30: SUBCONTRACTOR | Y30: SUBCONTRACTOR
B31: Mobilisation / Demobilisation Personnel | G31: SUBCONTRACTOR | J31: SUBCONTRACTOR | M31: SUBCONTRACTOR | P31: SUBCONTRACTOR | S31: SUBCONTRACTOR | V31: SUBCONTRACTOR | Y31: SUBCONTRACTOR
B32: DIESEL | G32: SUBCONTRACTOR | J32: SUBCONTRACTOR | M32: SUBCONTRACTOR | P32: SUBCONTRACTOR | S32: SUBCONTRACTOR | V32: SUBCONTRACTOR | Y32: SUBCONTRACTOR
B33: Accomodation | G33: SUBCONTRACTOR | J33: SUBCONTRACTOR | M33: SUBCONTRACTOR | P33: SUBCONTRACTOR | S33: SUBCONTRACTOR | V33: SUBCONTRACTOR | Y33: SUBCONTRACTOR
B34: Meal | G34: SUBCONTRACTOR | J34: SUBCONTRACTOR | M34: SUBCONTRACTOR | S34: SUBCONTRACTOR | V34: SUBCONTRACTOR | Y34: SUBCONTRACTOR
B35: REMARKS | M35: Minimum number of participants: 7 | P35: First Aid Training Offline only
B37: PURCHASE RECOMMENDATION:
B39: VENDOR: | F39: =J9
B41: REASON | F41: Lowest total price among valid bids
B43: CHECKED BY: | C43: PREPARED BY: | G43: APPROVED BY: | L43: AGREED BY:

Sheet Price Comparison
A1: CONTRACTOR PRICE COMPARISON
A2: Project | B2: =Sheet1!D4 | D2: Leader | E2: =IFERROR(INDEX($B$9:$B$15,MATCH(_xlfn.MINIFS($I$9:$I$15,$I$9:$I$15,">0"),$I$9:$I$15,0)),"—") | G2: Legend
A3: Procurement Item | B3: =Sheet1!D6 | D3: Best Price incl. VAT | E3: =IFERROR(_xlfn.MINIFS($I$9:$I$15,$I$9:$I$15,">0"),0) | G3: Best Price | H3: Green
A4: Last Updated | B4: 10.08.2026 | D4: Valid Bids | E4: =COUNTIF($I$9:$I$15,">0") | G4: Incomplete Data | H4: Yellow
A5: Source | B5: Sheet1 — Commercial Evaluation | D5: Savings vs. Highest Price | E5: =IF(COUNTIF($I$9:$I$15,">0")>1,MAX($I$9:$I$15)-_xlfn.MINIFS($I$9:$I$15,$I$9:$I$15,">0"),0) | G5: No Prices / Not Provided | H5: Red / Gray
A7: FINAL BID COMPARISON
A8: No. | B8: Vendor | C8: Offer No. | D8: Currency / Rate | E8: Priced Items | F8: Coverage | G8: Amount excl. VAT | H8: VAT | I8: Total incl. VAT | J8: Variance vs. Min | K8: Rank | L8: Payment Terms | M8: Remarks | N8: Status
A9: 1 | B9: {=IF(INDEX(Sheet1!$G$9:$AA$9,1,1+($A9-1)*3)<>"",INDEX(Sheet1!$G$9:$AA$9,1,1+($A9-1)*3),"Not provided")} | C9: {=IF(INDEX(Sheet1!$G$11:$AA$11,1,1+($A9-1)*3)="","",INDEX(Sheet1!$G$11:$AA$11,1,1+($A9-1)*3))} | D9: {=IF(INDEX(Sheet1!$G$9:$AA$9,1,1+($A9-1)*3)="","",IF(INDEX(Sheet1!$G$12:$AA$12,1,1+($A9-1)*3)="","KZT",INDEX(Sheet1!$G$12:$AA$12,1,1+($A9-1)*3)))} | E9: {=IF(INDEX(Sheet1!$G$9:$AA$9,1,1+($A9-1)*3)="","",COUNTIF(INDEX(Sheet1!$H$14:$AA$23,0,1+($A9-1)*3),">0"))} | F9: =IF(E9="","",E9/ROWS(Sheet1!$H$14:$H$23)) | G9: {=IF(INDEX(Sheet1!$G$9:$AA$9,1,1+($A9-1)*3)="","",INDEX(Sheet1!$H$24:$AA$24,1,1+($A9-1)*3))} | H9: {=IF(INDEX(Sheet1!$G$9:$AA$9,1,1+($A9-1)*3)="","",INDEX(Sheet1!$H$26:$AA$26,1,1+($A9-1)*3))} | I9: {=IF(INDEX(Sheet1!$G$9:$AA$9,1,1+($A9-1)*3)="","",INDEX(Sheet1!$G$27:$AA$27,1,1+($A9-1)*3))} | J9: =IF(OR(N9="Not provided",N9="No prices"),"",IFERROR(I9/$E$3-1,"")) | K9: =IF(OR(N9="Not provided",N9="No prices"),"",IFERROR(COUNTIFS($I$9:$I$15,">0",$I$9:$I$15,"<"&I9)+1,"")) | L9: {=IF(INDEX(Sheet1!$G$29:$AA$29,1,1+($A9-1)*3)="","",INDEX(Sheet1!$G$29:$AA$29,1,1+($A9-1)*3))} | M9: {=IF(INDEX(Sheet1!$G$35:$AA$35,1,1+($A9-1)*3)="","",INDEX(Sheet1!$G$35:$AA$35,1,1+($A9-1)*3))} | N9: =IF(B9="Not provided","Not provided",IF(I9<=0,"No prices",IF(F9<1,"Incomplete bid","Ready")))
A10: 2 | B10: {=IF(INDEX(Sheet1!$G$9:$AA$9,1,1+($A10-1)*3)<>"",INDEX(Sheet1!$G$9:$AA$9,1,1+($A10-1)*3),"Not provided")} | C10: {=IF(INDEX(Sheet1!$G$11:$AA$11,1,1+($A10-1)*3)="","",INDEX(Sheet1!$G$11:$AA$11,1,1+($A10-1)*3))} | D10: {=IF(INDEX(Sheet1!$G$9:$AA$9,1,1+($A10-1)*3)="","",IF(INDEX(Sheet1!$G$12:$AA$12,1,1+($A10-1)*3)="","KZT",INDEX(Sheet1!$G$12:$AA$12,1,1+($A10-1)*3)))} | E10: {=IF(INDEX(Sheet1!$G$9:$AA$9,1,1+($A10-1)*3)="","",COUNTIF(INDEX(Sheet1!$H$14:$AA$23,0,1+($A10-1)*3),">0"))} | F10: =IF(E10="","",E10/ROWS(Sheet1!$H$14:$H$23)) | G10: {=IF(INDEX(Sheet1!$G$9:$AA$9,1,1+($A10-1)*3)="","",INDEX(Sheet1!$H$24:$AA$24,1,1+($A10-1)*3))} | H10: {=IF(INDEX(Sheet1!$G$9:$AA$9,1,1+($A10-1)*3)="","",INDEX(Sheet1!$H$26:$AA$26,1,1+($A10-1)*3))} | I10: {=IF(INDEX(Sheet1!$G$9:$AA$9,1,1+($A10-1)*3)="","",INDEX(Sheet1!$G$27:$AA$27,1,1+($A10-1)*3))} | J10: =IF(OR(N10="Not provided",N10="No prices"),"",IFERROR(I10/$E$3-1,"")) | K10: =IF(OR(N10="Not provided",N10="No prices"),"",IFERROR(COUNTIFS($I$9:$I$15,">0",$I$9:$I$15,"<"&I10)+1,"")) | L10: {=IF(INDEX(Sheet1!$G$29:$AA$29,1,1+($A10-1)*3)="","",INDEX(Sheet1!$G$29:$AA$29,1,1+($A10-1)*3))} | M10: {=IF(INDEX(Sheet1!$G$35:$AA$35,1,1+($A10-1)*3)="","",INDEX(Sheet1!$G$35:$AA$35,1,1+($A10-1)*3))} | N10: =IF(B10="Not provided","Not provided",IF(I10<=0,"No prices",IF(F10<1,"Incomplete bid","Ready")))
A11: 3 | B11: {=IF(INDEX(Sheet1!$G$9:$AA$9,1,1+($A11-1)*3)<>"",INDEX(Sheet1!$G$9:$AA$9,1,1+($A11-1)*3),"Not provided")} | C11: {=IF(INDEX(Sheet1!$G$11:$AA$11,1,1+($A11-1)*3)="","",INDEX(Sheet1!$G$11:$AA$11,1,1+($A11-1)*3))} | D11: {=IF(INDEX(Sheet1!$G$9:$AA$9,1,1+($A11-1)*3)="","",IF(INDEX(Sheet1!$G$12:$AA$12,1,1+($A11-1)*3)="","KZT",INDEX(Sheet1!$G$12:$AA$12,1,1+($A11-1)*3)))} | E11: {=IF(INDEX(Sheet1!$G$9:$AA$9,1,1+($A11-1)*3)="","",COUNTIF(INDEX(Sheet1!$H$14:$AA$23,0,1+($A11-1)*3),">0"))} | F11: =IF(E11="","",E11/ROWS(Sheet1!$H$14:$H$23)) | G11: {=IF(INDEX(Sheet1!$G$9:$AA$9,1,1+($A11-1)*3)="","",INDEX(Sheet1!$H$24:$AA$24,1,1+($A11-1)*3))} | H11: {=IF(INDEX(Sheet1!$G$9:$AA$9,1,1+($A11-1)*3)="","",INDEX(Sheet1!$H$26:$AA$26,1,1+($A11-1)*3))} | I11: {=IF(INDEX(Sheet1!$G$9:$AA$9,1,1+($A11-1)*3)="","",INDEX(Sheet1!$G$27:$AA$27,1,1+($A11-1)*3))} | J11: =IF(OR(N11="Not provided",N11="No prices"),"",IFERROR(I11/$E$3-1,"")) | K11: =IF(OR(N11="Not provided",N11="No prices"),"",IFERROR(COUNTIFS($I$9:$I$15,">0",$I$9:$I$15,"<"&I11)+1,"")) | L11: {=IF(INDEX(Sheet1!$G$29:$AA$29,1,1+($A11-1)*3)="","",INDEX(Sheet1!$G$29:$AA$29,1,1+($A11-1)*3))} | M11: {=IF(INDEX(Sheet1!$G$35:$AA$35,1,1+($A11-1)*3)="","",INDEX(Sheet1!$G$35:$AA$35,1,1+($A11-1)*3))} | N11: =IF(B11="Not provided","Not provided",IF(I11<=0,"No prices",IF(F11<1,"Incomplete bid","Ready")))
A12: 4 | B12: {=IF(INDEX(Sheet1!$G$9:$AA$9,1,1+($A12-1)*3)<>"",INDEX(Sheet1!$G$9:$AA$9,1,1+($A12-1)*3),"Not provided")} | C12: {=IF(INDEX(Sheet1!$G$11:$AA$11,1,1+($A12-1)*3)="","",INDEX(Sheet1!$G$11:$AA$11,1,1+($A12-1)*3))} | D12: {=IF(INDEX(Sheet1!$G$9:$AA$9,1,1+($A12-1)*3)="","",IF(INDEX(Sheet1!$G$12:$AA$12,1,1+($A12-1)*3)="","KZT",INDEX(Sheet1!$G$12:$AA$12,1,1+($A12-1)*3)))} | E12: {=IF(INDEX(Sheet1!$G$9:$AA$9,1,1+($A12-1)*3)="","",COUNTIF(INDEX(Sheet1!$H$14:$AA$23,0,1+($A12-1)*3),">0"))} | F12: =IF(E12="","",E12/ROWS(Sheet1!$H$14:$H$23)) | G12: {=IF(INDEX(Sheet1!$G$9:$AA$9,1,1+($A12-1)*3)="","",INDEX(Sheet1!$H$24:$AA$24,1,1+($A12-1)*3))} | H12: {=IF(INDEX(Sheet1!$G$9:$AA$9,1,1+($A12-1)*3)="","",INDEX(Sheet1!$H$26:$AA$26,1,1+($A12-1)*3))} | I12: {=IF(INDEX(Sheet1!$G$9:$AA$9,1,1+($A12-1)*3)="","",INDEX(Sheet1!$G$27:$AA$27,1,1+($A12-1)*3))} | J12: =IF(OR(N12="Not provided",N12="No prices"),"",IFERROR(I12/$E$3-1,"")) | K12: =IF(OR(N12="Not provided",N12="No prices"),"",IFERROR(COUNTIFS($I$9:$I$15,">0",$I$9:$I$15,"<"&I12)+1,"")) | L12: {=IF(INDEX(Sheet1!$G$29:$AA$29,1,1+($A12-1)*3)="","",INDEX(Sheet1!$G$29:$AA$29,1,1+($A12-1)*3))} | M12: {=IF(INDEX(Sheet1!$G$35:$AA$35,1,1+($A12-1)*3)="","",INDEX(Sheet1!$G$35:$AA$35,1,1+($A12-1)*3))} | N12: =IF(B12="Not provided","Not provided",IF(I12<=0,"No prices",IF(F12<1,"Incomplete bid","Ready")))
A13: 5 | B13: {=IF(INDEX(Sheet1!$G$9:$AA$9,1,1+($A13-1)*3)<>"",INDEX(Sheet1!$G$9:$AA$9,1,1+($A13-1)*3),"Not provided")} | C13: {=IF(INDEX(Sheet1!$G$11:$AA$11,1,1+($A13-1)*3)="","",INDEX(Sheet1!$G$11:$AA$11,1,1+($A13-1)*3))} | D13: {=IF(INDEX(Sheet1!$G$9:$AA$9,1,1+($A13-1)*3)="","",IF(INDEX(Sheet1!$G$12:$AA$12,1,1+($A13-1)*3)="","KZT",INDEX(Sheet1!$G$12:$AA$12,1,1+($A13-1)*3)))} | E13: {=IF(INDEX(Sheet1!$G$9:$AA$9,1,1+($A13-1)*3)="","",COUNTIF(INDEX(Sheet1!$H$14:$AA$23,0,1+($A13-1)*3),">0"))} | F13: =IF(E13="","",E13/ROWS(Sheet1!$H$14:$H$23)) | G13: {=IF(INDEX(Sheet1!$G$9:$AA$9,1,1+($A13-1)*3)="","",INDEX(Sheet1!$H$24:$AA$24,1,1+($A13-1)*3))} | H13: {=IF(INDEX(Sheet1!$G$9:$AA$9,1,1+($A13-1)*3)="","",INDEX(Sheet1!$H$26:$AA$26,1,1+($A13-1)*3))} | I13: {=IF(INDEX(Sheet1!$G$9:$AA$9,1,1+($A13-1)*3)="","",INDEX(Sheet1!$G$27:$AA$27,1,1+($A13-1)*3))} | J13: =IF(OR(N13="Not provided",N13="No prices"),"",IFERROR(I13/$E$3-1,"")) | K13: =IF(OR(N13="Not provided",N13="No prices"),"",IFERROR(COUNTIFS($I$9:$I$15,">0",$I$9:$I$15,"<"&I13)+1,"")) | L13: {=IF(INDEX(Sheet1!$G$29:$AA$29,1,1+($A13-1)*3)="","",INDEX(Sheet1!$G$29:$AA$29,1,1+($A13-1)*3))} | M13: {=IF(INDEX(Sheet1!$G$35:$AA$35,1,1+($A13-1)*3)="","",INDEX(Sheet1!$G$35:$AA$35,1,1+($A13-1)*3))} | N13: =IF(B13="Not provided","Not provided",IF(I13<=0,"No prices",IF(F13<1,"Incomplete bid","Ready")))
A14: 6 | B14: {=IF(INDEX(Sheet1!$G$9:$AA$9,1,1+($A14-1)*3)<>"",INDEX(Sheet1!$G$9:$AA$9,1,1+($A14-1)*3),"Not provided")} | C14: {=IF(INDEX(Sheet1!$G$11:$AA$11,1,1+($A14-1)*3)="","",INDEX(Sheet1!$G$11:$AA$11,1,1+($A14-1)*3))} | D14: {=IF(INDEX(Sheet1!$G$9:$AA$9,1,1+($A14-1)*3)="","",IF(INDEX(Sheet1!$G$12:$AA$12,1,1+($A14-1)*3)="","KZT",INDEX(Sheet1!$G$12:$AA$12,1,1+($A14-1)*3)))} | E14: {=IF(INDEX(Sheet1!$G$9:$AA$9,1,1+($A14-1)*3)="","",COUNTIF(INDEX(Sheet1!$H$14:$AA$23,0,1+($A14-1)*3),">0"))} | F14: =IF(E14="","",E14/ROWS(Sheet1!$H$14:$H$23)) | G14: {=IF(INDEX(Sheet1!$G$9:$AA$9,1,1+($A14-1)*3)="","",INDEX(Sheet1!$H$24:$AA$24,1,1+($A14-1)*3))} | H14: {=IF(INDEX(Sheet1!$G$9:$AA$9,1,1+($A14-1)*3)="","",INDEX(Sheet1!$H$26:$AA$26,1,1+($A14-1)*3))} | I14: {=IF(INDEX(Sheet1!$G$9:$AA$9,1,1+($A14-1)*3)="","",INDEX(Sheet1!$G$27:$AA$27,1,1+($A14-1)*3))} | J14: =IF(OR(N14="Not provided",N14="No prices"),"",IFERROR(I14/$E$3-1,"")) | K14: =IF(OR(N14="Not provided",N14="No prices"),"",IFERROR(COUNTIFS($I$9:$I$15,">0",$I$9:$I$15,"<"&I14)+1,"")) | L14: {=IF(INDEX(Sheet1!$G$29:$AA$29,1,1+($A14-1)*3)="","",INDEX(Sheet1!$G$29:$AA$29,1,1+($A14-1)*3))} | M14: {=IF(INDEX(Sheet1!$G$35:$AA$35,1,1+($A14-1)*3)="","",INDEX(Sheet1!$G$35:$AA$35,1,1+($A14-1)*3))} | N14: =IF(B14="Not provided","Not provided",IF(I14<=0,"No prices",IF(F14<1,"Incomplete bid","Ready")))
A15: 7 | B15: {=IF(INDEX(Sheet1!$G$9:$AA$9,1,1+($A15-1)*3)<>"",INDEX(Sheet1!$G$9:$AA$9,1,1+($A15-1)*3),"Not provided")} | C15: {=IF(INDEX(Sheet1!$G$11:$AA$11,1,1+($A15-1)*3)="","",INDEX(Sheet1!$G$11:$AA$11,1,1+($A15-1)*3))} | D15: {=IF(INDEX(Sheet1!$G$9:$AA$9,1,1+($A15-1)*3)="","",IF(INDEX(Sheet1!$G$12:$AA$12,1,1+($A15-1)*3)="","KZT",INDEX(Sheet1!$G$12:$AA$12,1,1+($A15-1)*3)))} | E15: {=IF(INDEX(Sheet1!$G$9:$AA$9,1,1+($A15-1)*3)="","",COUNTIF(INDEX(Sheet1!$H$14:$AA$23,0,1+($A15-1)*3),">0"))} | F15: =IF(E15="","",E15/ROWS(Sheet1!$H$14:$H$23)) | G15: {=IF(INDEX(Sheet1!$G$9:$AA$9,1,1+($A15-1)*3)="","",INDEX(Sheet1!$H$24:$AA$24,1,1+($A15-1)*3))} | H15: {=IF(INDEX(Sheet1!$G$9:$AA$9,1,1+($A15-1)*3)="","",INDEX(Sheet1!$H$26:$AA$26,1,1+($A15-1)*3))} | I15: {=IF(INDEX(Sheet1!$G$9:$AA$9,1,1+($A15-1)*3)="","",INDEX(Sheet1!$G$27:$AA$27,1,1+($A15-1)*3))} | J15: =IF(OR(N15="Not provided",N15="No prices"),"",IFERROR(I15/$E$3-1,"")) | K15: =IF(OR(N15="Not provided",N15="No prices"),"",IFERROR(COUNTIFS($I$9:$I$15,">0",$I$9:$I$15,"<"&I15)+1,"")) | L15: {=IF(INDEX(Sheet1!$G$29:$AA$29,1,1+($A15-1)*3)="","",INDEX(Sheet1!$G$29:$AA$29,1,1+($A15-1)*3))} | M15: {=IF(INDEX(Sheet1!$G$35:$AA$35,1,1+($A15-1)*3)="","",INDEX(Sheet1!$G$35:$AA$35,1,1+($A15-1)*3))} | N15: =IF(B15="Not provided","Not provided",IF(I15<=0,"No prices",IF(F15<1,"Incomplete bid","Ready")))
A17: RECOMMENDATION AND REVIEW
A18: Recommended Vendor | B18: =IF(COUNTIF($I$9:$I$15,">0")=0,"No valid bids",INDEX($B$9:$B$15,MATCH(_xlfn.MINIFS($I$9:$I$15,$I$9:$I$15,">0"),$I$9:$I$15,0)))
A19: Price incl. VAT | B19: =IFERROR(_xlfn.MINIFS($I$9:$I$15,$I$9:$I$15,">0"),0)
A20: Rationale | B20: =IF(COUNTIF($I$9:$I$15,">0")=0,"Enter vendor prices.",IF(COUNTIF($I$9:$I$15,">0")=1,"Only one price quotation received — at least two are required for a meaningful comparison.","Lowest total price among valid bids;"))
A21: Review | B21: =IF(COUNTIF($I$9:$I$15,">0")<2,"Comparison is limited: fewer than two valid bids.","Comparison is ready for a commercial decision.")
A23: ITEM-BY-ITEM COMPARISON
A24: No. | B24: Service / Item | C24: Qty | D24: =$B$9 | E24: =$B$10 | F24: =$B$11 | G24: =$B$12 | H24: =$B$13 | I24: =$B$14 | J24: =$B$15 | M24: Lowest Price | N24: Best Vendor | O24: Variance vs. Min | P24: Status
A25: 1 | B25: =Sheet1!D14 | C25: =Sheet1!E14 | D25: =IF(Sheet1!H14>0,Sheet1!H14,"") | E25: =IF(Sheet1!K14>0,Sheet1!K14,"") | F25: =IF(Sheet1!N14>0,Sheet1!N14,"") | G25: =IF(Sheet1!Q14>0,Sheet1!Q14,"") | H25: =IF(Sheet1!T14>0,Sheet1!T14,"") | I25: =IF(Sheet1!W14>0,Sheet1!W14,"") | J25: =IF(Sheet1!Z14>0,Sheet1!Z14,"") | M25: =IF(COUNTIF(D25:L25,">0")=0,"",_xlfn.MINIFS(D25:L25,D25:L25,">0")) | N25: =IF(M25="","",INDEX($D$24:$L$24,1,MATCH(M25,D25:L25,0))) | O25: =IF(COUNTIF(D25:L25,">0")<2,"",MAX(D25:L25)/M25-1) | P25: =IF(COUNTIF(D25:L25,">0")=0,"No prices",IF(COUNTIF(D25:L25,">0")=1,"Only 1 price","Comparison available"))
A26: 2 | B26: =Sheet1!D15 | C26: =Sheet1!E15 | D26: =IF(Sheet1!H15>0,Sheet1!H15,"") | E26: =IF(Sheet1!K15>0,Sheet1!K15,"") | F26: =IF(Sheet1!N15>0,Sheet1!N15,"") | G26: =IF(Sheet1!Q15>0,Sheet1!Q15,"") | H26: =IF(Sheet1!T15>0,Sheet1!T15,"") | I26: =IF(Sheet1!W15>0,Sheet1!W15,"") | J26: =IF(Sheet1!Z15>0,Sheet1!Z15,"") | M26: =IF(COUNTIF(D26:L26,">0")=0,"",_xlfn.MINIFS(D26:L26,D26:L26,">0")) | N26: =IF(M26="","",INDEX($D$24:$L$24,1,MATCH(M26,D26:L26,0))) | O26: =IF(COUNTIF(D26:L26,">0")<2,"",MAX(D26:L26)/M26-1) | P26: =IF(COUNTIF(D26:L26,">0")=0,"No prices",IF(COUNTIF(D26:L26,">0")=1,"Only 1 price","Comparison available"))
A27: 3 | B27: =Sheet1!D16 | C27: =Sheet1!E16 | D27: =IF(Sheet1!H16>0,Sheet1!H16,"") | E27: =IF(Sheet1!K16>0,Sheet1!K16,"") | F27: =IF(Sheet1!N16>0,Sheet1!N16,"") | G27: =IF(Sheet1!Q16>0,Sheet1!Q16,"") | H27: =IF(Sheet1!T16>0,Sheet1!T16,"") | I27: =IF(Sheet1!W16>0,Sheet1!W16,"") | J27: =IF(Sheet1!Z16>0,Sheet1!Z16,"") | M27: =IF(COUNTIF(D27:L27,">0")=0,"",_xlfn.MINIFS(D27:L27,D27:L27,">0")) | N27: =IF(M27="","",INDEX($D$24:$L$24,1,MATCH(M27,D27:L27,0))) | O27: =IF(COUNTIF(D27:L27,">0")<2,"",MAX(D27:L27)/M27-1) | P27: =IF(COUNTIF(D27:L27,">0")=0,"No prices",IF(COUNTIF(D27:L27,">0")=1,"Only 1 price","Comparison available"))
A28: 4 | B28: =Sheet1!D17 | C28: =Sheet1!E17 | D28: =IF(Sheet1!H17>0,Sheet1!H17,"") | E28: =IF(Sheet1!K17>0,Sheet1!K17,"") | F28: =IF(Sheet1!N17>0,Sheet1!N17,"") | G28: =IF(Sheet1!Q17>0,Sheet1!Q17,"") | H28: =IF(Sheet1!T17>0,Sheet1!T17,"") | I28: =IF(Sheet1!W17>0,Sheet1!W17,"") | J28: =IF(Sheet1!Z17>0,Sheet1!Z17,"") | M28: =IF(COUNTIF(D28:L28,">0")=0,"",_xlfn.MINIFS(D28:L28,D28:L28,">0")) | N28: =IF(M28="","",INDEX($D$24:$L$24,1,MATCH(M28,D28:L28,0))) | O28: =IF(COUNTIF(D28:L28,">0")<2,"",MAX(D28:L28)/M28-1) | P28: =IF(COUNTIF(D28:L28,">0")=0,"No prices",IF(COUNTIF(D28:L28,">0")=1,"Only 1 price","Comparison available"))
A29: 5 | B29: =Sheet1!D18 | C29: =Sheet1!E18 | D29: =IF(Sheet1!H18>0,Sheet1!H18,"") | E29: =IF(Sheet1!K18>0,Sheet1!K18,"") | F29: =IF(Sheet1!N18>0,Sheet1!N18,"") | G29: =IF(Sheet1!Q18>0,Sheet1!Q18,"") | H29: =IF(Sheet1!T18>0,Sheet1!T18,"") | I29: =IF(Sheet1!W18>0,Sheet1!W18,"") | J29: =IF(Sheet1!Z18>0,Sheet1!Z18,"") | M29: =IF(COUNTIF(D29:L29,">0")=0,"",_xlfn.MINIFS(D29:L29,D29:L29,">0")) | N29: =IF(M29="","",INDEX($D$24:$L$24,1,MATCH(M29,D29:L29,0))) | O29: =IF(COUNTIF(D29:L29,">0")<2,"",MAX(D29:L29)/M29-1) | P29: =IF(COUNTIF(D29:L29,">0")=0,"No prices",IF(COUNTIF(D29:L29,">0")=1,"Only 1 price","Comparison available"))
A30: 6 | B30: =Sheet1!D19 | C30: =Sheet1!E19 | D30: =IF(Sheet1!H19>0,Sheet1!H19,"") | E30: =IF(Sheet1!K19>0,Sheet1!K19,"") | F30: =IF(Sheet1!N19>0,Sheet1!N19,"") | G30: =IF(Sheet1!Q19>0,Sheet1!Q19,"") | H30: =IF(Sheet1!T19>0,Sheet1!T19,"") | I30: =IF(Sheet1!W19>0,Sheet1!W19,"") | J30: =IF(Sheet1!Z19>0,Sheet1!Z19,"") | M30: =IF(COUNTIF(D30:L30,">0")=0,"",_xlfn.MINIFS(D30:L30,D30:L30,">0")) | N30: =IF(M30="","",INDEX($D$24:$L$24,1,MATCH(M30,D30:L30,0))) | O30: =IF(COUNTIF(D30:L30,">0")<2,"",MAX(D30:L30)/M30-1) | P30: =IF(COUNTIF(D30:L30,">0")=0,"No prices",IF(COUNTIF(D30:L30,">0")=1,"Only 1 price","Comparison available"))
A31: 7 | B31: =Sheet1!D20 | C31: =Sheet1!E20 | D31: =IF(Sheet1!H20>0,Sheet1!H20,"") | E31: =IF(Sheet1!K20>0,Sheet1!K20,"") | F31: =IF(Sheet1!N20>0,Sheet1!N20,"") | G31: =IF(Sheet1!Q20>0,Sheet1!Q20,"") | H31: =IF(Sheet1!T20>0,Sheet1!T20,"") | I31: =IF(Sheet1!W20>0,Sheet1!W20,"") | J31: =IF(Sheet1!Z20>0,Sheet1!Z20,"") | M31: =IF(COUNTIF(D31:L31,">0")=0,"",_xlfn.MINIFS(D31:L31,D31:L31,">0")) | N31: =IF(M31="","",INDEX($D$24:$L$24,1,MATCH(M31,D31:L31,0))) | O31: =IF(COUNTIF(D31:L31,">0")<2,"",MAX(D31:L31)/M31-1) | P31: =IF(COUNTIF(D31:L31,">0")=0,"No prices",IF(COUNTIF(D31:L31,">0")=1,"Only 1 price","Comparison available"))
A32: 8 | B32: =Sheet1!D21 | C32: =Sheet1!E21 | D32: =IF(Sheet1!H21>0,Sheet1!H21,"") | E32: =IF(Sheet1!K21>0,Sheet1!K21,"") | F32: =IF(Sheet1!N21>0,Sheet1!N21,"") | G32: =IF(Sheet1!Q21>0,Sheet1!Q21,"") | H32: =IF(Sheet1!T21>0,Sheet1!T21,"") | I32: =IF(Sheet1!W21>0,Sheet1!W21,"") | J32: =IF(Sheet1!Z21>0,Sheet1!Z21,"") | M32: =IF(COUNTIF(D32:L32,">0")=0,"",_xlfn.MINIFS(D32:L32,D32:L32,">0")) | N32: =IF(M32="","",INDEX($D$24:$L$24,1,MATCH(M32,D32:L32,0))) | O32: =IF(COUNTIF(D32:L32,">0")<2,"",MAX(D32:L32)/M32-1) | P32: =IF(COUNTIF(D32:L32,">0")=0,"No prices",IF(COUNTIF(D32:L32,">0")=1,"Only 1 price","Comparison available"))
A33: 9 | B33: =Sheet1!D22 | C33: =Sheet1!E22 | D33: =IF(Sheet1!H22>0,Sheet1!H22,"") | E33: =IF(Sheet1!K22>0,Sheet1!K22,"") | F33: =IF(Sheet1!N22>0,Sheet1!N22,"") | G33: =IF(Sheet1!Q22>0,Sheet1!Q22,"") | H33: =IF(Sheet1!T22>0,Sheet1!T22,"") | I33: =IF(Sheet1!W22>0,Sheet1!W22,"") | J33: =IF(Sheet1!Z22>0,Sheet1!Z22,"") | M33: =IF(COUNTIF(D33:L33,">0")=0,"",_xlfn.MINIFS(D33:L33,D33:L33,">0")) | N33: =IF(M33="","",INDEX($D$24:$L$24,1,MATCH(M33,D33:L33,0))) | O33: =IF(COUNTIF(D33:L33,">0")<2,"",MAX(D33:L33)/M33-1) | P33: =IF(COUNTIF(D33:L33,">0")=0,"No prices",IF(COUNTIF(D33:L33,">0")=1,"Only 1 price","Comparison available"))
A34: 10 | B34: =Sheet1!D23 | C34: =Sheet1!E23 | D34: =IF(Sheet1!H23>0,Sheet1!H23,"") | E34: =IF(Sheet1!K23>0,Sheet1!K23,"") | F34: =IF(Sheet1!N23>0,Sheet1!N23,"") | G34: =IF(Sheet1!Q23>0,Sheet1!Q23,"") | H34: =IF(Sheet1!T23>0,Sheet1!T23,"") | I34: =IF(Sheet1!W23>0,Sheet1!W23,"") | J34: =IF(Sheet1!Z23>0,Sheet1!Z23,"") | M34: =IF(COUNTIF(D34:L34,">0")=0,"",_xlfn.MINIFS(D34:L34,D34:L34,">0")) | N34: =IF(M34="","",INDEX($D$24:$L$24,1,MATCH(M34,D34:L34,0))) | O34: =IF(COUNTIF(D34:L34,">0")<2,"",MAX(D34:L34)/M34-1) | P34: =IF(COUNTIF(D34:L34,">0")=0,"No prices",IF(COUNTIF(D34:L34,">0")=1,"Only 1 price","Comparison available"))
